itly_plugin_amplitude/__init__.py
itly_plugin_amplitude/_amplitude_client.py
itly_plugin_amplitude/_amplitude_metadata.py
itly_plugin_amplitude/_amplitude_plugin.py
itly_plugin_amplitude-0.1.14.dist-info/WHEEL
itly_plugin_amplitude-0.1.14.dist-info/METADATA
itly_plugin_amplitude-0.1.14.dist-info/RECORD
